{
    "103050050": {
        "id": "103050050",
        "first_name": "Alexey",
        "username": "lexfrl",
        "bio": "Former core parity.io,near.org @movevm github.com/lexfrl, x.com/lex_frl. hobby project https://gofest.app"
    },
    "105650323": {
        "id": "105650323",
        "first_name": "Andrey",
        "username": "anyro",
        "bio": ""
    },
    "113449671": {
        "id": "113449671",
        "first_name": "Ilya",
        "username": "adenorth",
        "bio": "\ud83c\uddf3\ud83c\uddf1"
    },
    "136289559": {
        "id": "136289559",
        "first_name": "J",
        "username": "JFixby",
        "bio": "BNL \u043a\u043e\u0448\u0435\u043b\u0451\u043a: 0xB936F34E0DC54957d85d67bE83eF6d1f6c40eaE9"
    },
    "319527783": {
        "id": "319527783",
        "first_name": "Vladimir",
        "username": "mechmind",
        "bio": ""
    },
    "322429695": {
        "id": "322429695",
        "first_name": "Yaroslav",
        "username": "nanosvin",
        "bio": ""
    },
    "347526285": {
        "id": "347526285",
        "first_name": "ilya",
        "username": "h1m1u",
        "bio": "on-chain r&d"
    },
    "35066947": {
        "id": "35066947",
        "first_name": "Dimitriy",
        "username": "dimitrr",
        "bio": "Shadowy super coder"
    },
    "481473548": {
        "id": "481473548",
        "first_name": "Jeroen",
        "username": "eisenberg1399",
        "bio": ""
    },
    "5046078269": {
        "id": "5046078269",
        "first_name": "Yu",
        "username": "prmbjd",
        "bio": ""
    },
    "5286774480": {
        "id": "5286774480",
        "first_name": "Denis\ud83c\udf12",
        "username": "denissl14",
        "bio": "0xd866e0fbf3a1497d5d86f3a005fa7e84927e966d"
    },
    "5536384524": {
        "id": "5536384524",
        "first_name": "Sky Hawk",
        "username": "skyhawknine",
        "bio": ""
    },
    "5854392540": {
        "id": "5854392540",
        "first_name": "\u0416\u0438\u0440\u043d\u044b\u0439 \u041c\u0438\u0442\u0435\u043b\u044c",
        "username": "chaymoliah",
        "bio": ""
    },
    "6873884615": {
        "id": "6873884615",
        "first_name": ".",
        "username": "oolalo",
        "bio": "BNL wallet : 0x4372b982254189fB1B6a65adF0c90032617Dad7C"
    },
    "8061400892": {
        "id": "8061400892",
        "first_name": "Katrinn",
        "username": "katrunna",
        "bio": ""
    }
}
